tg_secret/__init__.py
tg_secret/aes.py
tg_secret/client.py
tg_secret/client_adapters/__init__.py
tg_secret/client_adapters/base_adapter.py
tg_secret/client_adapters/pyrogram_adapter.py
tg_secret/client_adapters/telethon_adapter.py
tg_secret/encrypted_file_wrapper.py
tg_secret/enums.py
tg_secret/exceptions.py
tg_secret/raw/.gitignore
tg_secret/raw/__init__.py
tg_secret/raw/all.py
tg_secret/raw/base/__init__.py
tg_secret/raw/primitives.py
tg_secret/raw/tl_object.py
tg_secret/raw/types/__init__.py
tg_secret/raw/vector.py
tg_secret/storage/__init__.py
tg_secret/storage/base_storage.py
tg_secret/storage/file_storage.py
tg_secret/storage/memory_storage.py
tg_secret/storage/sqlite_storage.py
tg_secret/types/__init__.py
tg_secret/types/secret_chat.py
tg_secret/types/secret_message.py
tg_secret/utils.py
tg_secret-0.1.3.dist-info/LICENSE
tg_secret-0.1.3.dist-info/METADATA
tg_secret-0.1.3.dist-info/WHEEL
tg_secret-0.1.3.dist-info/RECORD
