Metadata-Version: 2.1
Name: tg-secret
Version: 0.1.3
Summary: Secret chats support for Telegram (MTProto) client libraries
License: MIT
Author: RuslanUC
Author-email: dev_ruslan_uc@protonmail.com
Requires-Python: >=3.11,<4.0
Classifier: Framework :: AsyncIO
Classifier: Intended Audience :: Developers
Classifier: License :: OSI Approved :: MIT License
Classifier: Operating System :: OS Independent
Classifier: Programming Language :: Python
Classifier: Programming Language :: Python :: 3
Classifier: Programming Language :: Python :: 3.11
Classifier: Programming Language :: Python :: 3.12
Classifier: Programming Language :: Python :: 3 :: Only
Classifier: Programming Language :: Python :: 3.13
Classifier: Topic :: Internet
Classifier: Typing :: Typed
Project-URL: Homepage, https://github.com/RuslanUC/tg_secret
Project-URL: Repository, https://github.com/RuslanUC/tg_secret
